drf_firebase_token_auth/__init__.py
drf_firebase_token_auth/admin.py
drf_firebase_token_auth/apps.py
drf_firebase_token_auth/authentication.py
drf_firebase_token_auth/migrations/0001_initial.py
drf_firebase_token_auth/migrations/__init__.py
drf_firebase_token_auth/models.py
drf_firebase_token_auth/settings.py
drf_firebase_token_auth/tests.py
drf_firebase_token_auth/views.py
drf_firebase_token_auth-0.2.1.dist-info/LICENSE
drf_firebase_token_auth-0.2.1.dist-info/WHEEL
drf_firebase_token_auth-0.2.1.dist-info/METADATA
drf_firebase_token_auth-0.2.1.dist-info/RECORD
