Metadata-Version: 2.1
Name: drf-firebase-token-auth
Version: 0.2.1
Summary: Firebase token authentication for Django Rest Framework
Home-page: https://github.com/ronhe/drf-firebase-token-auth
License: MIT
Keywords: Django,Rest Framework,Firebase,Authentication,Token
Author: Ron Heimann
Author-email: ron.heimann@gmail.com
Requires-Python: >=3.6,<4.0
Classifier: Development Status :: 4 - Beta
Classifier: Environment :: Web Environment
Classifier: Framework :: Django
Classifier: Intended Audience :: Developers
Classifier: License :: OSI Approved :: MIT License
Classifier: Operating System :: OS Independent
Classifier: Programming Language :: Python
Classifier: Programming Language :: Python :: 3
Classifier: Programming Language :: Python :: 3.6
Classifier: Programming Language :: Python :: 3.7
Classifier: Programming Language :: Python :: 3.8
Classifier: Programming Language :: Python :: 3.9
Classifier: Topic :: Internet :: WWW/HTTP
Requires-Dist: firebase-admin (>=4.4.0,<5.0.0)
Requires-Dist: importlib-metadata (>=1.0,<2.0); python_version < "3.8"
Project-URL: Repository, https://github.com/ronhe/drf-firebase-token-auth
